coherence/__init__.py
coherence/backend.py
coherence/backends/__init__.py
coherence/backends/ampache_storage.py
coherence/backends/appletrailers_storage.py
coherence/backends/audiocd_storage.py
coherence/backends/axiscam_storage.py
coherence/backends/banshee_storage.py
coherence/backends/buzztard_control.py
coherence/backends/dvbd_storage.py
coherence/backends/elisa_renderer.py
coherence/backends/elisa_storage.py
coherence/backends/feed_storage.py
coherence/backends/flickr_storage.py
coherence/backends/fs_storage.py
coherence/backends/gallery2_storage.py
coherence/backends/gstreamer_renderer.py
coherence/backends/iradio_storage.py
coherence/backends/itv_storage.py
coherence/backends/lastfm_storage.py
coherence/backends/lolcats_storage.py
coherence/backends/mediadb_storage.py
coherence/backends/miroguide_storage.py
coherence/backends/models/__init__.py
coherence/backends/models/containers.py
coherence/backends/models/items.py
coherence/backends/models/stores.py
coherence/backends/picasa_storage.py
coherence/backends/playlist_storage.py
coherence/backends/radiotime_storage.py
coherence/backends/swr3_storage.py
coherence/backends/ted_storage.py
coherence/backends/test_storage.py
coherence/backends/tracker_storage.py
coherence/backends/twitch_storage.py
coherence/backends/yamj_storage.py
coherence/backends/youtube_storage.py
coherence/base.py
coherence/cli.py
coherence/dbus_constants.py
coherence/dbus_service.py
coherence/extern/__init__.py
coherence/extern/covers_by_amazon.py
coherence/extern/db_row.py
coherence/extern/galleryremote/__init__.py
coherence/extern/galleryremote/gallery.py
coherence/extern/simple_plugin.py
coherence/extern/xdg.py
coherence/extern/youtubedl/__init__.py
coherence/extern/youtubedl/youtubedl.py
coherence/json_service.py
coherence/log.py
coherence/transcoder.py
coherence/tube_service.py
coherence/upnp/__init__.py
coherence/upnp/core/DIDLLite.py
coherence/upnp/core/__init__.py
coherence/upnp/core/action.py
coherence/upnp/core/device.py
cohen3-0.9.3.dist-info/entry_points.txt
cohen3-0.9.3.dist-info/WHEEL
cohen3-0.9.3.dist-info/METADATA
cohen3-0.9.3.dist-info/RECORD
