Metadata-Version: 2.1
Name: cohen3
Version: 0.9.3
Summary: Cohen3 - DLNA/UPnP Media Server
Home-page: https://github.com/opacam/Cohen3/
License: MIT
Keywords: UPnP,DLNA,multimedia,gstreamer
Author: opacam
Author-email: canellestudi@gmail.com
Maintainer: opacam
Maintainer-email: canellestudi@gmail.com
Requires-Python: >=3.6,<4.0
Classifier: Development Status :: 4 - Beta
Classifier: Environment :: Console
Classifier: Environment :: Web Environment
Classifier: License :: OSI Approved :: MIT License
Classifier: Operating System :: OS Independent
Classifier: Programming Language :: Python :: 3
Classifier: Programming Language :: Python :: 3.6
Classifier: Programming Language :: Python :: 3.7
Classifier: Programming Language :: Python :: 3.8
Classifier: Topic :: Internet :: WWW/HTTP
Classifier: Topic :: Multimedia :: Sound/Audio
Classifier: Topic :: Multimedia :: Video
Classifier: Topic :: Utilities
Provides-Extra: audio
Provides-Extra: dbus
Provides-Extra: dev
Provides-Extra: docs
Provides-Extra: elisa
Provides-Extra: feed
Provides-Extra: gstreamer
Provides-Extra: picasa
Provides-Extra: test
Provides-Extra: twitch
Provides-Extra: web
Provides-Extra: youtube
Requires-Dist: autobahn; extra == "web" or extra == "dev"
Requires-Dist: configobj (>=4.3)
Requires-Dist: dbus-python; extra == "dbus" or extra == "dev"
Requires-Dist: eventdispatcher (==1.9.4)
Requires-Dist: feedparser; extra == "feed"
Requires-Dist: flake8; extra == "test" or extra == "dev"
Requires-Dist: livestreamer; extra == "twitch"
Requires-Dist: lxml
Requires-Dist: nose-cov; extra == "test" or extra == "dev"
Requires-Dist: nose; extra == "test" or extra == "dev"
Requires-Dist: pycairo (>=1.17.1); extra == "gstreamer" or extra == "dev"
Requires-Dist: pygobject (>=3.30.0); extra == "gstreamer" or extra == "dev"
Requires-Dist: pylint (==2.1.1); extra == "test" or extra == "dev"
Requires-Dist: pyopenssl
Requires-Dist: python-coveralls (==2.9.1); extra == "test" or extra == "dev"
Requires-Dist: python-dateutil
Requires-Dist: recommonmark (>=0.4.0); extra == "docs" or extra == "dev"
Requires-Dist: service_identity (>=18.1.0,<19.0.0)
Requires-Dist: sphinx (>=1.3.5); extra == "docs" or extra == "dev"
Requires-Dist: sphinx-rtd-theme (>=0.1.9); extra == "docs" or extra == "dev"
Requires-Dist: sphinxcontrib-napoleon (>=0.4.4); extra == "docs" or extra == "dev"
Requires-Dist: twisted (>=20.3.0)
Requires-Dist: zope.interface
Project-URL: Bug Tracker, https://github.com/opacam/Cohen3/issues
Project-URL: Documentation, https://opacam.github.io/Cohen3/
Project-URL: Repository, https://github.com/opacam/Cohen3/
